{
    "任务类型": "0-1代码生成",
    "业务领域": "角色扮演游戏(RPG)",
    "修改范围": "模块内多文件（涉及同一模块内的接口定义与实现协同）",
    "画面风格": "像素赛博朋克风",
    "音乐风格": "雷鬼音乐",
    "提示词内容": "请根据以下需求为我生成一个像素赛博朋克风格的网页角色扮演游戏，所有代码放在单个 HTML 文件中，用 Canvas 渲染画面，可直接双击打开运行。\n\n1. 游戏核心是角色扮演玩法：玩家控制一个主角，在 2D 俯视角的像素赛博朋克城市街区中移动，与 NPC 对话接取任务，进入回合制战斗来提升等级和获得装备。地图至少包含 3 个可进入的建筑和 5 个可交互的 NPC。\n2. 必须实现至少 3 个支线任务和 1 个主线任务链，任务的完成状态和对话内容根据玩家选择发生变化，对话系统要展示不同 NPC 的像素头像和名字。\n3. 战斗采用回合制，但需要你把雷鬼音乐的元素做成战斗技能，比如“低音冲击”、“节奏护盾”、“延时回血”这类技能，技能释放时会触发对应的雷鬼乐器音效和屏幕震动特效。至少要设计 5 种拥有不同属性和外观的敌人，以及 8 种可学习或可装备的技能。\n4. 画面统一为像素赛博朋克风：霓虹灯光边缘、深紫色与青色的主色调、雨滴颗粒效果、全屏 CRT 扫描线滤镜、发光的全息广告牌，人物和建筑都必须用像素精灵图绘制，不允许使用外部图片，所有图形通过代码绘制或生成。\n5. 背景音乐和音效必须贴合雷鬼音乐风格：城镇场景循环播放一段由你生成的雷鬼节奏背景乐，战斗场景切换为更紧凑的雷鬼战斗曲。使用 Web Audio API 合成所有音乐和音效，不能依赖任何外部音频文件。音效包含脚步、对话确认、技能释放、受击、升级等常规 RPG 音效，但都要处理成带有雷鬼反拍切分感的听感。\n6. 游戏通关或战败时，必须弹出一个评分窗口，根据你的任务完成数量、战斗胜利场次、角色等级和剩余生命值计算总分，并在窗口内显示带霓虹描边的等级评价文字（如“街头浪人”、“音响义体”、“雷鬼传奇”等），同时允许玩家重新开始。\n7. 实现一套简单的物品和装备系统：玩家可以打开背包查看和装备武器、防具、消耗品，装备会改变角色的攻击力、防御力和速度，物品栏至少要有 12 个格位，并支持丢弃和整理功能。（模糊需求：主角在装备不同品级装备时，外观像素图形需要出现对应的部位变化，你自己决定变化的方式和范围。）\n8. 需要包含一个“义体改造”的功能入口，玩家可以在义体医生 NPC 处花费游戏货币安装义体，义体会提供永久被动效果，但不能写清楚义体安装后是否会产生负面副作用，这个逻辑由你设计但要保持一定的不可预测性。\n9. 容易遗漏的细节：角色在雨中的地面倒影必须实时绘制；对话日志要保留最近 10 条，可以用方向键上下翻看；背包内物品长按时要弹出带像素描边的浮层详情；音量设置需要能分别调节背景音乐和音效的大小，并默认音量均为 70%。\n10. 可量化验证：Canvas 分辨率不低于 480x320，画面必须稳定在 60fps 左右；玩家初始等级为 1，最高可升至 20 级；文本渲染使用像素字体，所有文本支持英文和简体中文混排；游戏必须能在最新的 Chrome 和 Edge 浏览器中不报错地完整运行，初次加载到可操作的时间不能超过 6 秒。"
}