{
    "任务类型": "0-1代码生成",
    "业务领域": "角色扮演游戏(RPG)",
    "修改范围": "模块内多文件（涉及同一模块内的接口定义与实现协同）",
    "画面风格": "水墨中国风",
    "音乐风格": "爵士乐",
    "提示词内容": "按照以下需求给我生成一个可直接在浏览器中运行的单文件HTML游戏，类型为水墨中国风角色扮演游戏(RPG)，核心玩法是探索与回合制战斗，并使用爵士乐作为背景音乐和音效。要求代码采用模块化设计，至少分离地图、战斗、音频、UI四个模块，模块间通过明确的接口通信。具体需求如下：\n\n1. 技术栈：纯原生HTML/CSS/JavaScript，所有代码和内嵌资源全部写在一个HTML文件里，不得使用任何外部依赖或构建工具。画布用Canvas实现游戏主画面，CSS负责UI布局和对话框样式。音频模块可使用AudioContext动态生成爵士乐风格的背景音乐和音效，或引用可信的公共领域音乐链接，但必须封装为独立接口。\n\n2. 画面风格：场景、角色、战斗特效必须全程体现水墨中国风。地图中的山石、树木、建筑用毛笔笔触效果绘制，角色采用写意风格，移动和待机时带有轻微墨量晕染边缘。战斗中的招式动画需要呈现墨迹扩散、笔锋拖尾、朱砂红点缀等视觉元素。整体色调以黑白灰为主，UI和关键提示允许少量朱砂红。\n\n3. 音乐音效：背景音乐为带有爵士风情的循环乐段，要求至少包含钢琴、低音提琴和鼓刷的音色感。战斗中的音效也要有爵士特征，比如普通攻击音效类似鼓刷轻击，技能释放伴随爵士和弦刮奏，胜利音效为一段上扬的爵士小号乐句。音频模块需暴露playBGM、stopBGM、playSFX三个接口供其他模块调用。\n\n4. 模块划分与接口设计：代码必须清晰拆分为MapModule、BattleModule、AudioModule、UIModule四个模块，每个模块用立即执行函数或ES Module方式隔离作用域。各模块只通过对外公开的接口函数通信，例如地图模块提供getPlayerPosition、setEncounterCallback，战斗模块提供startBattle、endBattle，音频模块提供上述接口，UI模块提供showDialog、updateBattleUI、showScorePanel等。主控制器Game负责初始化和协调调用。\n\n5. 探索玩法：角色在至少包含竹林、山道、庭院三个不同场景的地图上以网格方式移动，通过键盘方向键控制。场景需有明显的画面过渡感。在特定图块或随机步数触发遇敌，进入回合制战斗。地图上放置至少一位可以对话的NPC，对话触发后用UI模块显示水墨风格对话框。\n\n6. 回合制战斗系统：遇敌后切换至战斗界面，显示出招命令菜单。玩家可选择普通攻击、技能（剑法、内功，消耗内力）、物品、逃跑。敌方AI执行普通攻击。技能需有不同的伤害数值和内力消耗，释放时显示对应水墨特效。战斗界面需实时显示玩家与敌人的生命值、内力值条。敌人生命归零则玩家胜利，玩家生命归零则游戏结束并显示重新开始选项。\n\n7. 模糊需求：战斗系统需要具备一定的策略深度，使玩家必须在有限的资源（生命、内力、物品）和敌人攻击模式之间做出有意义的决策，而不是纯数值碾压。\n\n8. 容易遗漏的细节：战斗胜利后需自动恢复角色最大生命值和内力值的一定比例；逃跑有失败概率，失败后本回合不能行动；需要实现一个简约的背包界面，能查看战斗中获得的道具；地图变暗或进入庭院等场景时背景音乐应平滑过渡，不可突然中断。\n\n9. 可量化验证的标准：在Chrome最新版中打开HTML文件，所有功能正常运行，控制台没有任何错误输出。战斗动画帧率稳定在30fps以上。所有文字在1366x768分辨率下清晰可读。BGM播放过程中无断流或卡顿感。\n\n10. 评分窗口：每次战斗结束后必须弹出水墨卷轴风格的评价窗口，根据玩家在本场战斗中的剩余生命值比例、总消耗回合数、是否使用技能造成有效连击等维度计算得分，并给出S/A/B/C等级评价和一句古风评语。评分窗口需要以卷轴展开动画呈现，卷轴背景为做旧宣纸质感，关闭后返回地图。"
}