{
    "任务类型": "0-1代码生成",
    "业务领域": "角色扮演游戏(RPG)",
    "修改范围": "模块内多文件（涉及同一模块内的接口定义与实现协同）",
    "画面风格": "赛博朋克风",
    "音乐风格": " ambient氛围音乐",
    "提示词内容": "按照以下需求为我生成一个可直接运行的HTML文件，包含一个赛博朋克风格的微型角色扮演游戏(RPG)。\n\n1. 游戏采用俯视视角，玩家通过键盘方向键或WASD控制一个角色在网格状地图上移动，地图至少包含20x15个格子，地图边界需要用赛博朋克风格的霓虹光墙封闭，不可走出。\n2. 角色有生命值、能量值、经验值和等级四个属性，初始生命值100点、能量值50点、经验值0点、等级1，界面上方需要以赛博朋克风格的HUD面板实时显示这些数值，数值变化时带有短暂的脉冲闪烁动画。\n3. 地图上随机散布着三种可交互实体：敌对无人机、中立商贩和可调查的数据终端，每种实体至少有5个实例，交互方式为移动到相邻格子时自动触发对话或战斗。\n4. 战斗系统采用简化回合制：接触敌对无人机后进入战斗模态，双方交替行动，玩家可选择“物理攻击”“能量攻击”或“逃跑”，物理攻击随机造成15-25点伤害，能量攻击消耗15点能量造成25-35点伤害，逃跑成功率50%。战斗胜利后获得经验值，经验值累积到当前等级所需经验值上限时升级，升级后生命值和能量值回满，并随机提升攻击力范围；战斗失败则生命值归零，游戏结束并显示赛博朋克风格的“义体报废”画面。\n5. 调查数据终端会触发一段随机的赛博朋克世界观文本片段，并有机会获得一次性使用的“数字护盾”道具，护盾效果是下一次战斗中免疫首回合伤害。道具需要显示在HUD的物品槽中，数量上限为3个。\n6. 中立商贩提供交易功能，用经验值换取随机临时强化效果，例如下一次物理攻击伤害提升50%等，交易后效果即时生效并在HUD上以状态图标显示剩余战斗次数。\n7. 整个游戏过程需要有ambient氛围音效作为背景音乐循环播放，音效使用Web Audio API合成，产生低沉持续的合成器铺底、偶尔出现的金属敲击声和远处电子干扰声。战斗状态切换时音乐不能中断，但可以叠加一层低频脉冲音效。\n8. 画面必须呈现明显的赛博朋克视觉风格：深色背景上用荧光青色品红线条绘制地图网格，角色和实体使用发光描边的像素风格图形，HUD元素带有扫描线效果和轻微抖动，数据终端和商贩周围有全息投影的光环。\n9. 游戏结束后根据玩家的等级、消灭敌人数量、收集的数据片段数量计算一个评价分数，并在一个覆盖全屏的半透明弹窗中展示评分等级，分为“街头菜鸟”“边缘行者”“赛博传奇”三档，同时提供重新开始按钮。\n10. 所有代码需封装在同一个HTML文件中，使用ES模块化结构划分地图管理、实体管理、战斗系统、音效系统和UI更新等职责，确保无外部依赖，点击即可运行。\n\n另外，当角色与商贩或数据终端交互后，需要在屏幕底部显示对话记录，最多保留最近5条，这个需求的具体触发条件和显示样式我没有详细说明，请自行设计合理的交互反馈。\n一个容易忽略的点是，当玩家打开物品栏使用护盾时，需要确认当前是否已在战斗中，非战斗状态使用应给出提示而不会消耗道具。\n\n验证标准：在不修改代码的前提下，通过手工操作能够完成从开局到触发战斗、使用道具、与终端交互、升级、最终死亡并看到评分界面的完整流程，且整个流程中HUD刷新率保持60fps无明显卡顿。"
}