{
    "任务类型": "0-1代码生成",
    "业务领域": "角色扮演游戏(RPG)",
    "修改范围": "模块内多文件（涉及同一模块内的接口定义与实现协同）",
    "画面风格": "卡通渲染风",
    "音乐风格": "爵士乐",
    "提示词内容": "按照以下需求给我生成一个可直接在浏览器中打开的单文件HTML游戏，该游戏是一个卡通渲染风格的角色扮演小游戏，并配有爵士乐背景音乐和音效。\n\n1. 游戏核心必须包含一个可操控的卡通角色在像素风格的俯视角地图上移动，地图至少包含三个不同主题的区域（如城镇、森林、洞穴），区域之间通过边界传送实现切换\n2. 画面必须使用canvas实现卡通渲染效果，具体要求：所有角色和场景元素采用粗描边加平涂色块，高光区域用纯白硬边形状表现，阴影用纯黑半透明硬边投影，整体配色以暖色为主并限制在16色调色板内\n3. 必须实现一个基于爵士乐风格的背景音乐系统，音乐不能使用任何外部资源，需通过Web Audio API合成，包含旋律、贝斯、鼓三个声部，节奏必须包含swing感，且进入战斗场景时音乐自动切换为更快速的变奏版本\n4. 必须实现一个非随机的回合制战斗系统，玩家和敌人都有攻击、防御、技能三个选项，技能消耗MP，防御可减少接下来一次受到的伤害，系统需要计算伤害时考虑角色属性，但具体计算公式你自己设计\n5. 战斗胜利后必须弹出一个评分窗口，根据战斗剩余HP百分比、使用技能次数、战斗回合数这三个维度进行星级评价（1到5星），并提供重新挑战或继续探索的按钮\n6. 角色属性至少包含HP、MP、攻击、防御、速度五个基础值，速度决定行动顺序，升级后属性提升方式你自己决定，必须实现一个简单的经验值和升级系统\n7. NPC对话必须实现逐字打印效果，且对话窗口需带有卡通风格的圆角边框和指向说话者的气泡三角，对话内容支持简单的分支选项，至少有一个NPC给出影响后续流程的关键选择\n8. 在实现物品系统时，背包界面中物品图标需要用程序化生成的小型卡通图案表现，而不是使用文字占位，消耗品使用后需要有短暂的动画反馈在角色身上\n9. 敌人种类至少设计三种，每种拥有不同的外观和技能模式，其中一种敌人必须拥有能让玩家陷入异常状态（如眩晕一回合）的技能\n10. 整个游戏的UI（血量条、按钮、状态面板）都必须统一成卡通涂鸦风格，所有文字使用无衬线粗体并添加手绘感的抖动描边，经验条必须设计成类似温度计上升的动画效果\n\n额外需要留意几个地方：我希望战斗背景能根据当前所处区域动态变化，但这个细节容易在场景切换时被忽略；还有关于爵士乐的音效反馈，除了背景音乐外，菜单选择、确认、取消、攻击命中、升级等事件都要有简短且风格统一的爵士乐小乐句作为音效，这部分不要漏掉；另外评分窗口的星星绘制必须用程序生成的矢量星星形状，不能用emoji或字符代替。"
}